{
    "type":"MCU",
    "name":"GD32E230",
    "Freq":"72MHz",
    "Core":"Cortex-M23",
    "title": "GigaDevice GD32E230 MCU",
    "description":"GigaDevice Cortex-M23 MCU",
    "manufacturer": {
        "vendor":"gigadevice",
        "homepage":"https://www.gigadevice.com/zh-hans/products/microcontrollers/gd32/arm-cortex-m4/?fwp_processor_type=cortex-m4&fwp_microcontrollers_product_series=GD32E230"
    },
    "repository": {
        "type": "git",
        "url": "https://github.com/SoCXin/GD32E230.git"
    },
    "version":"1.0.0",
    "series":["GD32E230KC","GD32E230JC","GD32E230KE","GD32E230PE"],
    "package":["UFBGA100","LQFP100","LQFP64","LQFP48","QFN60","QFN48"],
    "peripheral": ["ADC","UART","I2C","SPI","PWM"],
    "keywords": [
        "AES","DES","3DES","SM1","SM3","SM4","SM7","MD5","SHA1","SHA224","SHA256","CRC","TRANG",
        "ADC","DAC","SDIO","CAN","USB","I2S","SPI",
        "144MHz",
        "LQFP144","LQFP100","BGA176",
        "3.6V","1.8V"
    ]
}
